mapperFrontend/__init__.py
mapperFrontend/mapper_frontend.py
sabreMapper/__init__.py
sabreMapper/sabre_mapper.py
sabreMapper-0.1.0.dist-info/LICENSE
sabreMapper-0.1.0.dist-info/METADATA
sabreMapper-0.1.0.dist-info/WHEEL
sabreMapper-0.1.0.dist-info/top_level.txt
sabreMapper-0.1.0.dist-info/RECORD
