Metadata-Version: 2.1
Name: sabreMapper
Version: 0.1.0
Summary: Qiskit Sabre Mapper
Home-page: https://gitee.com/LTQUBIT/qiskit_sabre_mapper
Author: LT
Author-email: listenwetnessluo@163.com
Project-URL: Bug Tracker, https://gitee.com/LTQUBIT/qiskit_sabre_mapper/issues
Classifier: Programming Language :: Python :: 3 :: Only
Classifier: License :: OSI Approved :: Apache Software License
Classifier: Operating System :: OS Independent
Requires-Python: >=3.7
License-File: LICENSE
Requires-Dist: numpy
Requires-Dist: retworkx
Requires-Dist: qiskit (==0.38.0)
